fast_pydb.cpython-313-x86_64-linux-musl.so
fast_pydb-1.0.0.dist-info/METADATA
fast_pydb-1.0.0.dist-info/WHEEL
fast_pydb-1.0.0.dist-info/top_level.txt
fast_pydb-1.0.0.dist-info/RECORD
fast_pydb-1.0.0.dist-info/licenses/LICENSE
