Metadata-Version: 2.4
Name: fast_pydb
Version: 1.0.0
Summary: fast implementations of various utility functions
Author: puzzleYOU GmbH
License: MIT
License-File: LICENSE
Dynamic: author
Dynamic: license
Dynamic: license-file
Dynamic: summary
